log_safe/__init__.py
log_safe/config.py
log_safe/log_safe.py
log_safe-0.1.2.dist-info/LICENSE
log_safe-0.1.2.dist-info/METADATA
log_safe-0.1.2.dist-info/WHEEL
log_safe-0.1.2.dist-info/top_level.txt
log_safe-0.1.2.dist-info/RECORD
