Metadata-Version: 2.1
Name: log_safe
Version: 0.1.2
Summary: log_safe is a Python library that provides safe and efficient logging capabilities for multiprocessing applications. It ensures that logging is thread-safe and process-safe, making it ideal for complex, multi-process Python applications
Home-page: https://github.com/solaikannanpandiyan/log_safe
Author: Solaikannan Pandiyan
Author-email: solaikannanpandiyan@gmail.com
Classifier: Programming Language :: Python :: 3
Classifier: License :: OSI Approved :: MIT License
Classifier: Operating System :: OS Independent
Requires-Python: >=3.6
License-File: LICENSE
